deep_motility
