Metadata-Version: 2.1
Name: Deep-Motility
Version: 1.0.3rc1
Summary: Deep Learning methods for the classification and segmentation of motility images
Home-page: https://github.com/joheras/Deep-Motility
Author: Jónathan Heras
Author-email: joheras@gmail.com
Maintainer: Jónathan Heras
Maintainer-email: joheras@gmail.com
License: GNU General Public License v3 (GPLv3)
Keywords: deep learning semantic segmentation pytorch motility classification
Platform: UNKNOWN
Classifier: Development Status :: 5 - Production/Stable
Classifier: Intended Audience :: Science/Research
Classifier: Intended Audience :: Healthcare Industry
Classifier: Intended Audience :: Developers
Classifier: Topic :: Scientific/Engineering :: Bio-Informatics
Classifier: Topic :: Scientific/Engineering :: Medical Science Apps.
Classifier: Topic :: Scientific/Engineering :: Image Recognition
Classifier: Topic :: Scientific/Engineering :: Artificial Intelligence
Classifier: License :: OSI Approved :: GNU General Public License v3 (GPLv3)
Classifier: Programming Language :: Python :: 3.6
Classifier: Programming Language :: Python :: 3.7
Classifier: Programming Language :: Python :: 3.8
